ergolog/__init__.py
ergolog/ergolog.py
ergolog-0.1.2.dist-info/licenses/LICENSE
ergolog-0.1.2.dist-info/METADATA
ergolog-0.1.2.dist-info/WHEEL
ergolog-0.1.2.dist-info/top_level.txt
ergolog-0.1.2.dist-info/RECORD
