Metadata-Version: 2.4
Name: ergolog
Version: 0.1.2
Summary: A minimal, ergonomic python logging wrapper
Author-email: David Kincaid <daelonsuzuka@gmail.com>
License-Expression: MIT
Project-URL: Homepage, https://github.com/DaelonSuzuka/ergolog
Project-URL: Documentation, https://github.com/DaelonSuzuka/ergolog
Project-URL: Repository, https://github.com/DaelonSuzuka/ergolog
Project-URL: Issues, https://github.com/DaelonSuzuka/ergolog/issues
Classifier: Development Status :: 4 - Beta
Classifier: Intended Audience :: Developers
Classifier: Operating System :: OS Independent
Classifier: Programming Language :: Python :: 3
Classifier: Programming Language :: Python :: 3.9
Classifier: Programming Language :: Python :: 3.10
Classifier: Programming Language :: Python :: 3.11
Classifier: Programming Language :: Python :: 3.12
Classifier: Programming Language :: Python :: 3.13
Requires-Python: >=3.9
License-File: LICENSE
Dynamic: license-file
